radvelso/__init__.py
radvelso/cthinning/__init__.py
radvelso/cthinning/cthinning.py
radvelso/evaluation/__init__.py
radvelso/evaluation/omp.py
radvelso/evaluation/radvelso_evaluation.py
radvelso/evaluation/radvelso_evaluation_sqlite.py
radvelso/evaluation/radvelso_evaluation_sqlite_plot.py
radvelso/fill_ray/__init__.py
radvelso/fill_ray/fill_ray.py
radvelso/graphics/__init__.py
radvelso/graphics/plot_ppi_test.py
radvelso/graphics/sqlite_to_plot_elevation_data_time.py
radvelso/qcavg/__init__.py
radvelso/qcavg/qcavg.py
radvelso/tests/__init__.py
radvelso/tests/unittest_superobs.py
radvelso/unravel/__init__.py
radvelso/unravel/continuity.py
radvelso/unravel/core.py
radvelso/unravel/dealias.py
radvelso/unravel/debug.py
radvelso/unravel/filtering.py
radvelso/unravel/find_reference.py
radvelso/unravel/initialisation.py
radvelso-2.0.6.dist-info/METADATA
radvelso-2.0.6.dist-info/WHEEL
radvelso-2.0.6.dist-info/top_level.txt
radvelso-2.0.6.dist-info/RECORD
