Metadata-Version: 2.1
Name: radvelso
Version: 2.0.6
Summary: radvelso's tools for superobs
Home-page: https://gitlab.science.gc.ca/dlo001/radvelso
Author: David Lobon
Author-email: dhlobon@gmail.com
License: GPL-3.0-or-later
Requires-Python: >=3.8
Requires-Dist: matplotlib
Requires-Dist: numpy (>=1.17.0)
Requires-Dist: cartopy (>=0.18.0)
Requires-Dist: h5py
Requires-Dist: packaging
Requires-Dist: pygrib
Requires-Dist: domutils
Requires-Dist: dask
Requires-Dist: scipy
Requires-Dist: pytz
